MANIFEST.in
README.md
setup.cfg
setup.py
blighty/__init__.py
blighty/_brush.py
blighty/_extended_context.py
blighty/legacy.py
blighty.egg-info/PKG-INFO
blighty.egg-info/SOURCES.txt
blighty.egg-info/dependency_links.txt
blighty.egg-info/requires.txt
blighty.egg-info/top_level.txt
blighty/gtk/__init__.py
blighty/gtk/canvas.py
blighty/x11/__init__.py
blighty/x11/_x11module.c
blighty/x11/atelier.c
blighty/x11/atelier.h
blighty/x11/base_canvas.c
blighty/x11/base_canvas.h
blighty/x11/canvas.py
blighty/x11/pycairo.h