Metadata-Version: 2.1
Name: blighty
Version: 3.0.0
Summary: Desktop Widget Manager. Think of conky, but with Python instead of Lua.
Home-page: https://github.com/P403n1x87/blighty
Author: Gabriele N. Tornetta
Author-email: phoenix1987@gmail.com
License: UNKNOWN
Project-URL: Bug Reports, https://github.com/P403n1x87/blighty/issues
Project-URL: Source, https://github.com/P403n1x87/blighty
Keywords: desklet widget infotainment
Platform: UNKNOWN
Classifier: Development Status :: 5 - Production/Stable
Classifier: Intended Audience :: Developers
Classifier: Topic :: Software Development :: Build Tools
Classifier: License :: OSI Approved :: GNU General Public License v3 (GPLv3)
Classifier: Programming Language :: Python :: 3
Classifier: Programming Language :: Python :: 3.4
Classifier: Programming Language :: Python :: 3.5
Classifier: Programming Language :: Python :: 3.6
Provides-Extra: test
